trytond/modules/cashbook_account/README.rst
trytond/modules/cashbook_account/__init__.py
trytond/modules/cashbook_account/book.py
trytond/modules/cashbook_account/book.xml
trytond/modules/cashbook_account/category.py
trytond/modules/cashbook_account/category.xml
trytond/modules/cashbook_account/configuration.py
trytond/modules/cashbook_account/configuration.xml
trytond/modules/cashbook_account/line.py
trytond/modules/cashbook_account/line.xml
trytond/modules/cashbook_account/message.xml
trytond/modules/cashbook_account/move.py
trytond/modules/cashbook_account/move.xml
trytond/modules/cashbook_account/netmixin.py
trytond/modules/cashbook_account/splitline.py
trytond/modules/cashbook_account/splitline.xml
trytond/modules/cashbook_account/tax.py
trytond/modules/cashbook_account/tax.xml
trytond/modules/cashbook_account/tryton.cfg
trytond/modules/cashbook_account/versiondep.txt
trytond/modules/cashbook_account/locale/de.po
trytond/modules/cashbook_account/locale/en.po
trytond/modules/cashbook_account/tests/__init__.py
trytond/modules/cashbook_account/tests/category.py
trytond/modules/cashbook_account/tests/line.py
trytond/modules/cashbook_account/tests/test_module.py
trytond/modules/cashbook_account/view/book_form.xml
trytond/modules/cashbook_account/view/book_list.xml
trytond/modules/cashbook_account/view/category_form.xml
trytond/modules/cashbook_account/view/category_list.xml
trytond/modules/cashbook_account/view/category_tree.xml
trytond/modules/cashbook_account/view/configuration_form.xml
trytond/modules/cashbook_account/view/line_form.xml
trytond/modules/cashbook_account/view/split_form.xml
trytond/modules/cashbook_account/view/tax_form.xml
trytond/modules/cashbook_account/view/tax_list.xml
mds_cashbook_account-7.0.14.dist-info/METADATA
mds_cashbook_account-7.0.14.dist-info/WHEEL
mds_cashbook_account-7.0.14.dist-info/entry_points.txt
mds_cashbook_account-7.0.14.dist-info/top_level.txt
mds_cashbook_account-7.0.14.dist-info/RECORD
